README.md
setup.cfg
setup.py
pipreqsnb/__init__.py
pipreqsnb/pipreqsnb.py
pipreqsnb.egg-info/PKG-INFO
pipreqsnb.egg-info/SOURCES.txt
pipreqsnb.egg-info/dependency_links.txt
pipreqsnb.egg-info/entry_points.txt
pipreqsnb.egg-info/not-zip-safe
pipreqsnb.egg-info/requires.txt
pipreqsnb.egg-info/top_level.txt