Metadata-Version: 2.1
Name: pipreqsnb
Version: 0.2.1
Summary: Pipreqs with jupyter notebook support
Home-page: https://github.com/ivanlen/pipreqsnb
Author: Ivan Lengyel
Author-email: ivalengy@gmail.com
License: MIT License
Platform: UNKNOWN
